[{"id":"3ac35e9b-1786-3cc0-be0c-ae0c60ef3a71","score":100,"count":1,"title":"כמו צמח בר","status":"Official","text-representation":{"language":"heb","script":"Hebr"},"artist-credit":[{"name":"חוה אלברשטיין","artist":{"id":"b6f36ff7-d252-498f-99b4-1937b00b386c","name":"חוה אלברשטיין","sort-name":"Alberstein, Chava"}}],"release-group":{"id":"b43f8115-96a9-357b-95d7-229ecb613334","type-id":"f529b476-6e62-324f-b0aa-1f3e33d313fc","title":"כמו צמח בר","primary-type":"Album"},"date":"1975","country":"IL","release-events":[{"date":"1975","area":{"id":"03691455-bb46-37e3-91d2-cb064a35ffcc","name":"Israel","sort-name":"Israel","iso-3166-1-codes":["IL"]}}],"label-info":[{"label":{"id":"b8d33bec-92cc-40d9-bd92-4eb089b401a9","name":"CBS"}}],"track-count":12,"media":[{"format":"Vinyl","disc-count":0,"track-count":12}]},{"id":"c9beef4b-12f9-43ff-adef-63da0cc9ac14","score":100,"count":1,"title":"First Edition","status":"Official","packaging":{"id":"f7101ce3-0384-39ce-9fde-fbbd0044d35f","name":"Cardboard/Paper Sleeve"},"text-representation":{"language":"heb","script":"Hebr"},"artist-credit":[{"name":"Danny Maseng","artist":{"id":"fd8ac7f8-6c26-4834-ade6-6d9314c36888","name":"Danny Maseng","sort-name":"Maseng, Danny"}}],"release-group":{"id":"7e7a4006-2fe3-4b98-9d45-fcf0e6ae4e85","type-id":"f529b476-6e62-324f-b0aa-1f3e33d313fc","title":"First Edition","primary-type":"Album"},"date":"1975","country":"IL","release-events":[{"date":"1975","area":{"id":"03691455-bb46-37e3-91d2-cb064a35ffcc","name":"Israel","sort-name":"Israel","iso-3166-1-codes":["IL"]}}],"barcode":"","label-info":[{"catalog-number":"DD 30874","label":{"id":"5a906bd8-2fc2-415f-935d-80ae7abcca8a","name":"התקליט"}}],"track-count":12,"media":[{"format":"Vinyl","disc-count":0,"track-count":12}],"tags":[{"count":1,"name":"danny maseng"},{"count":1,"name":"דני מסנג"}]},{"id":"71de912c-40bc-4c9e-bd36-7d6eb883fbce","score":100,"count":1,"title":"שירים","status":"Official","text-representation":{"language":"heb","script":"Hebr"},"artist-credit":[{"name":"אריק איינשטיין","artist":{"id":"d3c90d1b-f529-404b-939d-41873386d4b4","name":"אריק איינשטיין","sort-name":"Einstein, Arik"}}],"release-group":{"id":"0c2f4036-bbaa-46af-bec1-138d67299e38","type-id":"f529b476-6e62-324f-b0aa-1f3e33d313fc","title":"שירים","primary-type":"Album"},"date":"1975","country":"IL","release-events":[{"date":"1975","area":{"id":"03691455-bb46-37e3-91d2-cb064a35ffcc","name":"Israel","sort-name":"Israel","iso-3166-1-codes":["IL"]}}],"label-info":[{"label":{"id":"229590d4-0a97-4dae-a40f-c4a1db7e2bfa","name":"פונוקול"}}],"track-count":10,"media":[{"disc-count":0,"track-count":10}]},{"id":"f1c907a0-5803-4680-92a7-ed155758fef6","score":100,"count":1,"title":"14 אוקטבות","status":"Official","packaging":{"id":"119eba76-b343-3e02-a292-f0f00644bb9b","name":"None"},"text-representation":{"language":"heb","script":"Hebr"},"artist-credit":[{"name":"14 אוקטבות","artist":{"id":"744a9cce-c60d-459e-abc8-08ad7aa38fe7","name":"ארבע עשרה אוקטבות","sort-name":"Arba Esrey Oktavot"}}],"release-group":{"id":"0832c681-0fc2-383f-a3e7-f521fa0f1d0d","type-id":"f529b476-6e62-324f-b0aa-1f3e33d313fc","title":"ארבע-עשרה אוקטבות","primary-type":"Album"},"date":"1975","country":"IL","release-events":[{"date":"1975","area":{"id":"03691455-bb46-37e3-91d2-cb064a35ffcc","name":"Israel","sort-name":"Israel","iso-3166-1-codes":["IL"]}}],"label-info":[{"label":{"id":"a488f2f6-a261-44d7-8985-e25ff0969eb7","name":"Helicon Records"}}],"track-count":12,"media":[{"disc-count":0,"track-count":12}]}]